README.md
setup.py
888.egg-info/PKG-INFO
888.egg-info/SOURCES.txt
888.egg-info/dependency_links.txt
888.egg-info/top_level.txt
wu/__init__.py
wu/wy.py