Metadata-Version: 2.1
Name: 888
Version: 0.0.0
Summary: A daily useful kit by WU.
Home-page: https://github.com/username/wu.git
Author: WU
License: MIT
Platform: all
Requires-Python: >=3.6.0
